Metadata-Version: 2.1
Name: gramps-cli
Version: 5.2.0rc1
Summary: Gramps (Genealogical Research and Analysis Management Programming System)
Home-page: http://gramps-project.org
Author: Donald N. Allingham
Author-email: don@gramps-project.org
Maintainer: Gramps Development Team
Maintainer-email: benny.malengier@gmail.com
License: GPL v2 or greater
Platform: FreeBSD
Platform: Linux
Platform: MacOS
Platform: Windows
Classifier: Development Status :: 4 - Beta
Classifier: Environment :: Console
Classifier: Environment :: MacOS X
Classifier: Environment :: Plugins
Classifier: Environment :: Web Environment
Classifier: Environment :: Win32 (MS Windows)
Classifier: Environment :: X11 Applications :: GTK
Classifier: Intended Audience :: Education
Classifier: Intended Audience :: End Users/Desktop
Classifier: Intended Audience :: Other Audience
Classifier: Intended Audience :: Science/Research
Classifier: License :: OSI Approved :: GNU General Public License v2 (GPLv2)
Classifier: Natural Language :: Arabic
Classifier: Natural Language :: Bulgarian
Classifier: Natural Language :: Catalan
Classifier: Natural Language :: Chinese (Simplified)
Classifier: Natural Language :: Croatian
Classifier: Natural Language :: Czech
Classifier: Natural Language :: Danish
Classifier: Natural Language :: Dutch
Classifier: Natural Language :: English
Classifier: Natural Language :: Esperanto
Classifier: Natural Language :: Finnish
Classifier: Natural Language :: French
Classifier: Natural Language :: German
Classifier: Natural Language :: Greek
Classifier: Natural Language :: Hebrew
Classifier: Natural Language :: Hungarian
Classifier: Natural Language :: Icelandic
Classifier: Natural Language :: Italian
Classifier: Natural Language :: Japanese
Classifier: Natural Language :: Macedonian
Classifier: Natural Language :: Norwegian
Classifier: Natural Language :: Polish
Classifier: Natural Language :: Portuguese
Classifier: Natural Language :: Portuguese (Brazilian)
Classifier: Natural Language :: Romanian
Classifier: Natural Language :: Russian
Classifier: Natural Language :: Serbian
Classifier: Natural Language :: Slovak
Classifier: Natural Language :: Slovenian
Classifier: Natural Language :: Spanish
Classifier: Natural Language :: Swedish
Classifier: Natural Language :: Turkish
Classifier: Natural Language :: Vietnamese
Classifier: Operating System :: MacOS
Classifier: Operating System :: Microsoft :: Windows
Classifier: Operating System :: Other OS
Classifier: Operating System :: POSIX :: BSD
Classifier: Operating System :: POSIX :: Linux
Classifier: Operating System :: POSIX :: SunOS/Solaris
Classifier: Operating System :: Unix
Classifier: Programming Language :: Python
Classifier: Programming Language :: Python :: 3
Classifier: Topic :: Database
Classifier: Topic :: Desktop Environment :: Gnome
Classifier: Topic :: Education
Classifier: Topic :: Scientific/Engineering :: Visualization
Classifier: Topic :: Sociology :: Genealogy
License-File: COPYING
License-File: AUTHORS
Provides-Extra: gui
Requires-Dist: PyGObject ; extra == 'gui'
Requires-Dist: pycairo ; extra == 'gui'
Provides-Extra: bsddb
Requires-Dist: bsddb3 ; extra == 'bsddb'
Provides-Extra: i18n
Requires-Dist: PyICU ; extra == 'i18n'
Provides-Extra: image
Requires-Dist: Pillow ; extra == 'image'
Provides-Extra: testing
Requires-Dist: jsonschema ; extra == 'testing'
Requires-Dist: mock ; extra == 'testing'
Requires-Dist: lxml ; extra == 'testing'
